s_sambuca-0.3.1.dist-info/DESCRIPTION.rst
s_sambuca-0.3.1.dist-info/METADATA
s_sambuca-0.3.1.dist-info/RECORD
s_sambuca-0.3.1.dist-info/WHEEL
s_sambuca-0.3.1.dist-info/metadata.json
s_sambuca-0.3.1.dist-info/top_level.txt
s_sambuca-0.3.1.dist-info/zip-safe
sambuca/__init__.py
sambuca/all_parameters.py
sambuca/all_parameters_hardcode.py
sambuca/array_result_writer.py
sambuca/error.py
sambuca/free_parameters.py
sambuca/minimize_wrapper.py
sambuca/pixel_result_handler.py
sambuca/sambuca.py
sambuca/scipy_objective.py
sambuca/tests/__init__.py
sambuca/tests/test_error_no_noise.py
sambuca/tests/test_error_noise.py
sambuca/tests/data/no_noise_error_data.sav
sambuca/tests/data/noise_error_data.sav
